jenky/__init__.py
jenky/__main__.py
jenky/git_helper.py
jenky/logging.py
jenky/server.py
jenky/test_jenky.py
jenky/util.py
jenky/html/graph.html
jenky/html/index.html
jenky/html/jenky_object_model.png
jenky/html/types.d.ts
jenky/html/ui.png
jenky-0.3.1.dist-info/LICENSE
jenky-0.3.1.dist-info/METADATA
jenky-0.3.1.dist-info/WHEEL
jenky-0.3.1.dist-info/top_level.txt
jenky-0.3.1.dist-info/RECORD
